{
 "name": "convolution_0",
 "src": "edlenet_0_C_1_4.cl",
 "workDimension": 1,
 "globalWorkSize": "[8192,1,1]",
 "inputBuffers": [
  {
    "break": 0,
    "type": "float",
    "size": "1024",
    "pos": 0,
    "persistence": 0
  },
  {
    "break": 0,
    "type": "float",
    "size": "288",
    "pos": 1,
    "persistence": 1
  },
  {
    "break": 0,
    "type": "float",
    "size": "32",
    "pos": 2,
    "persistence": 1
  }
 ],
 "outputBuffers": [
  {
    "break": 0,
    "type": "float",
    "size": "32768",
    "pos": 3,
    "persistence": 0
  }
 ]
}
